coder_search_mcp/__init__.py
coder_search_mcp/main.py
coder_search_mcp/schemas/__init__.py
coder_search_mcp/schemas/tool.py
coder_search_mcp/utils/__init__.py
coder_search_mcp/utils/tool.py
coder_search_mcp-1.0.4.dist-info/METADATA
coder_search_mcp-1.0.4.dist-info/WHEEL
coder_search_mcp-1.0.4.dist-info/entry_points.txt
coder_search_mcp-1.0.4.dist-info/top_level.txt
coder_search_mcp-1.0.4.dist-info/RECORD
