Metadata-Version: 2.4
Name: coder-search-mcp
Version: 1.0.4
Summary: Coder Search MCP Server
Author-email: Petr Grigorev <grigoryev.pete@gmail.com>
Requires-Python: >=3.10
Requires-Dist: httpx>=0.28.1
Requires-Dist: mcp[cli]>=1.12.3
Requires-Dist: pydantic>=2.11.7
